utils/__init__.py
utils/console.py
utils/constants.py
utils/helpers.py
utils/py.typed
vadi/__init__.py
vadi/interpreter.py
vadi/lexer.py
vadi/memory.py
vadi/parser.py
vadi/py.typed
vadi/repl.py
vadi/tokens.py
vadi/typedef.py
vadi-0.0.7.dist-info/LICENSE
vadi-0.0.7.dist-info/METADATA
vadi-0.0.7.dist-info/WHEEL
vadi-0.0.7.dist-info/entry_points.txt
vadi-0.0.7.dist-info/RECORD
