Metadata-Version: 2.1
Name: vadi
Version: 0.0.7
Summary: REPL of a simple, interpreted and statically-typed programming language.
Home-page: https://github.com/vyogami/Vadi
Author: Shivam Shandilya
Author-email: fvyogami@gmail.com
Requires-Python: >=3.10,<4.0
Classifier: Programming Language :: Python :: 3
Classifier: Programming Language :: Python :: 3.10
Classifier: Programming Language :: Python :: 3.11
Classifier: Programming Language :: Python :: 3.12
Requires-Dist: prompt-toolkit (>=3.0.43,<4.0.0)
Requires-Dist: rich (>=13.7.1,<14.0.0)
Project-URL: Documentation, https://github.com/vyogami/Vadi/blob/main/CONTRIBUTING.md
Project-URL: Repository, https://github.com/vyogami/Vadi
